{"protocol":{"minReaderVersion":1,"minWriterVersion":2}}
{"metaData":{"id":"9323cd54-994a-4f1b-80e1-2180b9dc2919","name":null,"description":null,"format":{"provider":"parquet","options":{}},"schemaString":"{\"type\":\"struct\",\"fields\":[{\"name\":\"Players per Age\",\"type\":\"long\",\"nullable\":true,\"metadata\":{}},{\"name\":\"age\",\"type\":\"double\",\"nullable\":true,\"metadata\":{}}]}","partitionColumns":["age"],"createdTime":1724559584469,"configuration":{}}}
{"add":{"path":"age=17/0-fe5cd186-73b7-4565-b8fc-488cb6700910-0.parquet","partitionValues":{"age":"17"},"size":628,"modificationTime":1724559584460,"dataChange":true,"stats":"{\"numRecords\": 1, \"minValues\": {\"Players per Age\": 8}, \"maxValues\": {\"Players per Age\": 8}, \"nullCount\": {\"Players per Age\": 0}}","tags":null,"deletionVector":null,"baseRowId":null,"defaultRowCommitVersion":null,"clusteringProvider":null}}
{"add":{"path":"age=18/0-fe5cd186-73b7-4565-b8fc-488cb6700910-0.parquet","partitionValues":{"age":"18"},"size":628,"modificationTime":1724559584461,"dataChange":true,"stats":"{\"numRecords\": 1, \"minValues\": {\"Players per Age\": 21}, \"maxValues\": {\"Players per Age\": 21}, \"nullCount\": {\"Players per Age\": 0}}","tags":null,"deletionVector":null,"baseRowId":null,"defaultRowCommitVersion":null,"clusteringProvider":null}}
{"add":{"path":"age=20/0-fe5cd186-73b7-4565-b8fc-488cb6700910-0.parquet","partitionValues":{"age":"20"},"size":628,"modificationTime":1724559584461,"dataChange":true,"stats":"{\"numRecords\": 1, \"minValues\": {\"Players per Age\": 32}, \"maxValues\": {\"Players per Age\": 32}, \"nullCount\": {\"Players per Age\": 0}}","tags":null,"deletionVector":null,"baseRowId":null,"defaultRowCommitVersion":null,"clusteringProvider":null}}
{"add":{"path":"age=33/0-fe5cd186-73b7-4565-b8fc-488cb6700910-0.parquet","partitionValues":{"age":"33"},"size":628,"modificationTime":1724559584461,"dataChange":true,"stats":"{\"numRecords\": 1, \"minValues\": {\"Players per Age\": 11}, \"maxValues\": {\"Players per Age\": 11}, \"nullCount\": {\"Players per Age\": 0}}","tags":null,"deletionVector":null,"baseRowId":null,"defaultRowCommitVersion":null,"clusteringProvider":null}}
{"add":{"path":"age=37/0-fe5cd186-73b7-4565-b8fc-488cb6700910-0.parquet","partitionValues":{"age":"37"},"size":628,"modificationTime":1724559584462,"dataChange":true,"stats":"{\"numRecords\": 1, \"minValues\": {\"Players per Age\": 3}, \"maxValues\": {\"Players per Age\": 3}, \"nullCount\": {\"Players per Age\": 0}}","tags":null,"deletionVector":null,"baseRowId":null,"defaultRowCommitVersion":null,"clusteringProvider":null}}
{"add":{"path":"age=22/0-fe5cd186-73b7-4565-b8fc-488cb6700910-0.parquet","partitionValues":{"age":"22"},"size":628,"modificationTime":1724559584462,"dataChange":true,"stats":"{\"numRecords\": 1, \"minValues\": {\"Players per Age\": 51}, \"maxValues\": {\"Players per Age\": 51}, \"nullCount\": {\"Players per Age\": 0}}","tags":null,"deletionVector":null,"baseRowId":null,"defaultRowCommitVersion":null,"clusteringProvider":null}}
{"add":{"path":"age=36/0-fe5cd186-73b7-4565-b8fc-488cb6700910-0.parquet","partitionValues":{"age":"36"},"size":628,"modificationTime":1724559584462,"dataChange":true,"stats":"{\"numRecords\": 1, \"minValues\": {\"Players per Age\": 3}, \"maxValues\": {\"Players per Age\": 3}, \"nullCount\": {\"Players per Age\": 0}}","tags":null,"deletionVector":null,"baseRowId":null,"defaultRowCommitVersion":null,"clusteringProvider":null}}
{"add":{"path":"age=23/0-fe5cd186-73b7-4565-b8fc-488cb6700910-0.parquet","partitionValues":{"age":"23"},"size":628,"modificationTime":1724559584463,"dataChange":true,"stats":"{\"numRecords\": 1, \"minValues\": {\"Players per Age\": 44}, \"maxValues\": {\"Players per Age\": 44}, \"nullCount\": {\"Players per Age\": 0}}","tags":null,"deletionVector":null,"baseRowId":null,"defaultRowCommitVersion":null,"clusteringProvider":null}}
{"add":{"path":"age=26/0-fe5cd186-73b7-4565-b8fc-488cb6700910-0.parquet","partitionValues":{"age":"26"},"size":628,"modificationTime":1724559584463,"dataChange":true,"stats":"{\"numRecords\": 1, \"minValues\": {\"Players per Age\": 48}, \"maxValues\": {\"Players per Age\": 48}, \"nullCount\": {\"Players per Age\": 0}}","tags":null,"deletionVector":null,"baseRowId":null,"defaultRowCommitVersion":null,"clusteringProvider":null}}
{"add":{"path":"age=19/0-fe5cd186-73b7-4565-b8fc-488cb6700910-0.parquet","partitionValues":{"age":"19"},"size":628,"modificationTime":1724559584463,"dataChange":true,"stats":"{\"numRecords\": 1, \"minValues\": {\"Players per Age\": 22}, \"maxValues\": {\"Players per Age\": 22}, \"nullCount\": {\"Players per Age\": 0}}","tags":null,"deletionVector":null,"baseRowId":null,"defaultRowCommitVersion":null,"clusteringProvider":null}}
{"add":{"path":"age=24/0-fe5cd186-73b7-4565-b8fc-488cb6700910-0.parquet","partitionValues":{"age":"24"},"size":628,"modificationTime":1724559584464,"dataChange":true,"stats":"{\"numRecords\": 1, \"minValues\": {\"Players per Age\": 50}, \"maxValues\": {\"Players per Age\": 50}, \"nullCount\": {\"Players per Age\": 0}}","tags":null,"deletionVector":null,"baseRowId":null,"defaultRowCommitVersion":null,"clusteringProvider":null}}
{"add":{"path":"age=21/0-fe5cd186-73b7-4565-b8fc-488cb6700910-0.parquet","partitionValues":{"age":"21"},"size":628,"modificationTime":1724559584464,"dataChange":true,"stats":"{\"numRecords\": 1, \"minValues\": {\"Players per Age\": 43}, \"maxValues\": {\"Players per Age\": 43}, \"nullCount\": {\"Players per Age\": 0}}","tags":null,"deletionVector":null,"baseRowId":null,"defaultRowCommitVersion":null,"clusteringProvider":null}}
{"add":{"path":"age=39/0-fe5cd186-73b7-4565-b8fc-488cb6700910-0.parquet","partitionValues":{"age":"39"},"size":628,"modificationTime":1724559584464,"dataChange":true,"stats":"{\"numRecords\": 1, \"minValues\": {\"Players per Age\": 3}, \"maxValues\": {\"Players per Age\": 3}, \"nullCount\": {\"Players per Age\": 0}}","tags":null,"deletionVector":null,"baseRowId":null,"defaultRowCommitVersion":null,"clusteringProvider":null}}
{"add":{"path":"age=30/0-fe5cd186-73b7-4565-b8fc-488cb6700910-0.parquet","partitionValues":{"age":"30"},"size":628,"modificationTime":1724559584465,"dataChange":true,"stats":"{\"numRecords\": 1, \"minValues\": {\"Players per Age\": 23}, \"maxValues\": {\"Players per Age\": 23}, \"nullCount\": {\"Players per Age\": 0}}","tags":null,"deletionVector":null,"baseRowId":null,"defaultRowCommitVersion":null,"clusteringProvider":null}}
{"add":{"path":"age=32/0-fe5cd186-73b7-4565-b8fc-488cb6700910-0.parquet","partitionValues":{"age":"32"},"size":628,"modificationTime":1724559584465,"dataChange":true,"stats":"{\"numRecords\": 1, \"minValues\": {\"Players per Age\": 26}, \"maxValues\": {\"Players per Age\": 26}, \"nullCount\": {\"Players per Age\": 0}}","tags":null,"deletionVector":null,"baseRowId":null,"defaultRowCommitVersion":null,"clusteringProvider":null}}
{"add":{"path":"age=34/0-fe5cd186-73b7-4565-b8fc-488cb6700910-0.parquet","partitionValues":{"age":"34"},"size":628,"modificationTime":1724559584465,"dataChange":true,"stats":"{\"numRecords\": 1, \"minValues\": {\"Players per Age\": 10}, \"maxValues\": {\"Players per Age\": 10}, \"nullCount\": {\"Players per Age\": 0}}","tags":null,"deletionVector":null,"baseRowId":null,"defaultRowCommitVersion":null,"clusteringProvider":null}}
{"add":{"path":"age=27/0-fe5cd186-73b7-4565-b8fc-488cb6700910-0.parquet","partitionValues":{"age":"27"},"size":628,"modificationTime":1724559584465,"dataChange":true,"stats":"{\"numRecords\": 1, \"minValues\": {\"Players per Age\": 49}, \"maxValues\": {\"Players per Age\": 49}, \"nullCount\": {\"Players per Age\": 0}}","tags":null,"deletionVector":null,"baseRowId":null,"defaultRowCommitVersion":null,"clusteringProvider":null}}
{"add":{"path":"age=31/0-fe5cd186-73b7-4565-b8fc-488cb6700910-0.parquet","partitionValues":{"age":"31"},"size":628,"modificationTime":1724559584465,"dataChange":true,"stats":"{\"numRecords\": 1, \"minValues\": {\"Players per Age\": 30}, \"maxValues\": {\"Players per Age\": 30}, \"nullCount\": {\"Players per Age\": 0}}","tags":null,"deletionVector":null,"baseRowId":null,"defaultRowCommitVersion":null,"clusteringProvider":null}}
{"add":{"path":"age=28/0-fe5cd186-73b7-4565-b8fc-488cb6700910-0.parquet","partitionValues":{"age":"28"},"size":628,"modificationTime":1724559584465,"dataChange":true,"stats":"{\"numRecords\": 1, \"minValues\": {\"Players per Age\": 40}, \"maxValues\": {\"Players per Age\": 40}, \"nullCount\": {\"Players per Age\": 0}}","tags":null,"deletionVector":null,"baseRowId":null,"defaultRowCommitVersion":null,"clusteringProvider":null}}
{"add":{"path":"age=25/0-fe5cd186-73b7-4565-b8fc-488cb6700910-0.parquet","partitionValues":{"age":"25"},"size":628,"modificationTime":1724559584467,"dataChange":true,"stats":"{\"numRecords\": 1, \"minValues\": {\"Players per Age\": 50}, \"maxValues\": {\"Players per Age\": 50}, \"nullCount\": {\"Players per Age\": 0}}","tags":null,"deletionVector":null,"baseRowId":null,"defaultRowCommitVersion":null,"clusteringProvider":null}}
{"add":{"path":"age=29/0-fe5cd186-73b7-4565-b8fc-488cb6700910-0.parquet","partitionValues":{"age":"29"},"size":628,"modificationTime":1724559584467,"dataChange":true,"stats":"{\"numRecords\": 1, \"minValues\": {\"Players per Age\": 26}, \"maxValues\": {\"Players per Age\": 26}, \"nullCount\": {\"Players per Age\": 0}}","tags":null,"deletionVector":null,"baseRowId":null,"defaultRowCommitVersion":null,"clusteringProvider":null}}
{"add":{"path":"age=38/0-fe5cd186-73b7-4565-b8fc-488cb6700910-0.parquet","partitionValues":{"age":"38"},"size":628,"modificationTime":1724559584467,"dataChange":true,"stats":"{\"numRecords\": 1, \"minValues\": {\"Players per Age\": 2}, \"maxValues\": {\"Players per Age\": 2}, \"nullCount\": {\"Players per Age\": 0}}","tags":null,"deletionVector":null,"baseRowId":null,"defaultRowCommitVersion":null,"clusteringProvider":null}}
{"add":{"path":"age=35/0-fe5cd186-73b7-4565-b8fc-488cb6700910-0.parquet","partitionValues":{"age":"35"},"size":628,"modificationTime":1724559584467,"dataChange":true,"stats":"{\"numRecords\": 1, \"minValues\": {\"Players per Age\": 3}, \"maxValues\": {\"Players per Age\": 3}, \"nullCount\": {\"Players per Age\": 0}}","tags":null,"deletionVector":null,"baseRowId":null,"defaultRowCommitVersion":null,"clusteringProvider":null}}
{"commitInfo":{"timestamp":1724559584469,"operation":"CREATE TABLE","operationParameters":{"location":"file:///D:/Cursos/Data%2520Engineering%2520UTN%2520e-learning/Codigo/Proyecto/data_lake/gold/players_per_age","protocol":"{\"minReaderVersion\":1,\"minWriterVersion\":2}","metadata":"{\"configuration\":{},\"createdTime\":1724559584469,\"description\":null,\"format\":{\"options\":{},\"provider\":\"parquet\"},\"id\":\"9323cd54-994a-4f1b-80e1-2180b9dc2919\",\"name\":null,\"partitionColumns\":[\"age\"],\"schemaString\":\"{\\\"type\\\":\\\"struct\\\",\\\"fields\\\":[{\\\"name\\\":\\\"Players per Age\\\",\\\"type\\\":\\\"long\\\",\\\"nullable\\\":true,\\\"metadata\\\":{}},{\\\"name\\\":\\\"age\\\",\\\"type\\\":\\\"double\\\",\\\"nullable\\\":true,\\\"metadata\\\":{}}]}\"}","mode":"ErrorIfExists"},"clientVersion":"delta-rs.0.18.1"}}